itunesLibrary/__init__.py
itunesLibrary/library.py
itunesLibrary/parser.py
iTunesLibrary-1.2.1.dist-info/LICENSE
iTunesLibrary-1.2.1.dist-info/METADATA
iTunesLibrary-1.2.1.dist-info/WHEEL
iTunesLibrary-1.2.1.dist-info/top_level.txt
iTunesLibrary-1.2.1.dist-info/RECORD
