Metadata-Version: 2.1
Name: iTunesLibrary
Version: 1.2.1
Summary: Represents an iTunes library
Home-page: https://github.com/scholnicks/itunes-library
Download-URL: https://github.com/scholnicks/itunes-library
Author: Steven Scholnick
Author-email: scholnicks@gmail.com
License: MIT
Keywords: iTunesLibrary,iTunes
Classifier: Development Status :: 5 - Production/Stable
Classifier: Topic :: Utilities
Classifier: Programming Language :: Python :: 3.13
Classifier: License :: OSI Approved :: MIT License
License-File: LICENSE
